<?xml version='1.1' encoding='UTF-8'?>
<list>
  <flow-owner plugin="workflow-job@2.42">
    <job>runEdgecloud</job>
    <id>1149</id>
  </flow-owner>
  <flow-owner plugin="workflow-job@2.42">
    <job>runCrmTests</job>
    <id>798</id>
  </flow-owner>
  <flow-owner plugin="workflow-job@2.42">
    <job>runCrmOpenstackSharedTests</job>
    <id>626</id>
  </flow-owner>
  <flow-owner plugin="workflow-job@2.42">
    <job>runCrmOpenstackDedicatedTests</job>
    <id>631</id>
  </flow-owner>
  <flow-owner plugin="workflow-job@2.42">
    <job>runCrmOpenstackDedicatedTests</job>
    <id>632</id>
  </flow-owner>
  <flow-owner plugin="workflow-job@2.42">
    <job>runCrmOpenstackSharedTests</job>
    <id>628</id>
  </flow-owner>
  <flow-owner plugin="workflow-job@2.42">
    <job>runCrmRunCommandTests</job>
    <id>926</id>
  </flow-owner>
  <flow-owner plugin="workflow-job@2.42">
    <job>runCrmOpenstackDedicatedTests</job>
    <id>633</id>
  </flow-owner>
  <flow-owner plugin="workflow-job@2.42">
    <job>runCrmGcpTests</job>
    <id>661</id>
  </flow-owner>
  <flow-owner plugin="workflow-job@2.42">
    <job>runCrmOpenstackVmTests</job>
    <id>593</id>
  </flow-owner>
  <flow-owner plugin="workflow-job@2.42">
    <job>runCrmOpenstackVmTests</job>
    <id>594</id>
  </flow-owner>
  <flow-owner plugin="workflow-job@2.42">
    <job>runCrmOpenstackDedicatedTests</job>
    <id>634</id>
  </flow-owner>
  <flow-owner plugin="workflow-job@2.42">
    <job>runCrmOpenstackSharedTests</job>
    <id>627</id>
  </flow-owner>
</list>